{
"20001" : {"attID" : 20001, "icon" : 101, "attName" : 20001115, "instructions" : 20001215, "customNum" : 4, "custom_0" : 1001, "custom_1" : 1002, "custom_2" : 1003, "custom_3" : 1004, "custom_4" : 0, "custom_5" : 0, "custom_6" : 0, "custom_7" : 0, "custom_8" : 0, "custom_9" : 0, "hellCustom_0" : 91001, "hellCustom_1" : 91002, "hellCustom_2" : 91003, "hellCustom_3" : 91004, "hellCustom_4" : 0, "hellCustom_5" : 0, "hellCustom_6" : 0, "hellCustom_7" : 0, "hellCustom_8" : 0, "hellCustom_9" : 0, "teamCustom" : 0, "giftNum" : 2, "giftID_0" : 4021, "giftID_1" : 4010, "giftID_2" : 0, "giftID_3" : 0, "giftID_4" : 0}, 
"20002" : {"attID" : 20002, "icon" : 102, "attName" : 20002115, "instructions" : 20002215, "customNum" : 6, "custom_0" : 2001, "custom_1" : 2002, "custom_2" : 2003, "custom_3" : 2004, "custom_4" : 2005, "custom_5" : 2006, "custom_6" : 0, "custom_7" : 0, "custom_8" : 0, "custom_9" : 0, "hellCustom_0" : 92001, "hellCustom_1" : 92002, "hellCustom_2" : 92003, "hellCustom_3" : 92004, "hellCustom_4" : 92005, "hellCustom_5" : 92006, "hellCustom_6" : 0, "hellCustom_7" : 0, "hellCustom_8" : 0, "hellCustom_9" : 0, "teamCustom" : 920002, "giftNum" : 2, "giftID_0" : 4022, "giftID_1" : 4011, "giftID_2" : 0, "giftID_3" : 0, "giftID_4" : 0}, 
"20003" : {"attID" : 20003, "icon" : 101, "attName" : 20003115, "instructions" : 20003215, "customNum" : 7, "custom_0" : 3001, "custom_1" : 3002, "custom_2" : 3003, "custom_3" : 3004, "custom_4" : 3005, "custom_5" : 3006, "custom_6" : 3007, "custom_7" : 0, "custom_8" : 0, "custom_9" : 0, "hellCustom_0" : 93001, "hellCustom_1" : 93002, "hellCustom_2" : 93003, "hellCustom_3" : 93004, "hellCustom_4" : 93005, "hellCustom_5" : 93006, "hellCustom_6" : 93007, "hellCustom_7" : 0, "hellCustom_8" : 0, "hellCustom_9" : 0, "teamCustom" : 920001, "giftNum" : 2, "giftID_0" : 4023, "giftID_1" : 4012, "giftID_2" : 0, "giftID_3" : 0, "giftID_4" : 0}, 
"20004" : {"attID" : 20004, "icon" : 102, "attName" : 20004115, "instructions" : 20004215, "customNum" : 7, "custom_0" : 4001, "custom_1" : 4002, "custom_2" : 4003, "custom_3" : 4004, "custom_4" : 4005, "custom_5" : 4006, "custom_6" : 4007, "custom_7" : 0, "custom_8" : 0, "custom_9" : 0, "hellCustom_0" : 94001, "hellCustom_1" : 94002, "hellCustom_2" : 94003, "hellCustom_3" : 94004, "hellCustom_4" : 94005, "hellCustom_5" : 94006, "hellCustom_6" : 94007, "hellCustom_7" : 0, "hellCustom_8" : 0, "hellCustom_9" : 0, "teamCustom" : 920003, "giftNum" : 2, "giftID_0" : 4024, "giftID_1" : 4013, "giftID_2" : 0, "giftID_3" : 0, "giftID_4" : 0}, 
"20005" : {"attID" : 20005, "icon" : 101, "attName" : 20005115, "instructions" : 20005215, "customNum" : 7, "custom_0" : 5001, "custom_1" : 5002, "custom_2" : 5003, "custom_3" : 5004, "custom_4" : 5005, "custom_5" : 5006, "custom_6" : 5007, "custom_7" : 0, "custom_8" : 0, "custom_9" : 0, "hellCustom_0" : 95001, "hellCustom_1" : 95002, "hellCustom_2" : 95003, "hellCustom_3" : 95004, "hellCustom_4" : 95005, "hellCustom_5" : 95006, "hellCustom_6" : 95007, "hellCustom_7" : 0, "hellCustom_8" : 0, "hellCustom_9" : 0, "teamCustom" : 920004, "giftNum" : 2, "giftID_0" : 4025, "giftID_1" : 4014, "giftID_2" : 0, "giftID_3" : 0, "giftID_4" : 0}, 
"20006" : {"attID" : 20006, "icon" : 102, "attName" : 20006115, "instructions" : 20006215, "customNum" : 7, "custom_0" : 6001, "custom_1" : 6002, "custom_2" : 6003, "custom_3" : 6004, "custom_4" : 6005, "custom_5" : 6006, "custom_6" : 6007, "custom_7" : 0, "custom_8" : 0, "custom_9" : 0, "hellCustom_0" : 96001, "hellCustom_1" : 96002, "hellCustom_2" : 96003, "hellCustom_3" : 96004, "hellCustom_4" : 96005, "hellCustom_5" : 96006, "hellCustom_6" : 96007, "hellCustom_7" : 0, "hellCustom_8" : 0, "hellCustom_9" : 0, "teamCustom" : 920005, "giftNum" : 2, "giftID_0" : 4026, "giftID_1" : 4015, "giftID_2" : 0, "giftID_3" : 0, "giftID_4" : 0}, 
"20007" : {"attID" : 20007, "icon" : 101, "attName" : 20007115, "instructions" : 20007215, "customNum" : 7, "custom_0" : 7001, "custom_1" : 7002, "custom_2" : 7003, "custom_3" : 7004, "custom_4" : 7005, "custom_5" : 7006, "custom_6" : 7007, "custom_7" : 0, "custom_8" : 0, "custom_9" : 0, "hellCustom_0" : 97001, "hellCustom_1" : 97002, "hellCustom_2" : 97003, "hellCustom_3" : 97004, "hellCustom_4" : 97005, "hellCustom_5" : 97006, "hellCustom_6" : 97007, "hellCustom_7" : 0, "hellCustom_8" : 0, "hellCustom_9" : 0, "teamCustom" : 920006, "giftNum" : 2, "giftID_0" : 4027, "giftID_1" : 4016, "giftID_2" : 0, "giftID_3" : 0, "giftID_4" : 0}, 
"20008" : {"attID" : 20008, "icon" : 102, "attName" : 20008115, "instructions" : 20008215, "customNum" : 7, "custom_0" : 8001, "custom_1" : 8002, "custom_2" : 8003, "custom_3" : 8004, "custom_4" : 8005, "custom_5" : 8006, "custom_6" : 8007, "custom_7" : 0, "custom_8" : 0, "custom_9" : 0, "hellCustom_0" : 98001, "hellCustom_1" : 98002, "hellCustom_2" : 98003, "hellCustom_3" : 98004, "hellCustom_4" : 98005, "hellCustom_5" : 98006, "hellCustom_6" : 98007, "hellCustom_7" : 0, "hellCustom_8" : 0, "hellCustom_9" : 0, "teamCustom" : 920007, "giftNum" : 2, "giftID_0" : 4028, "giftID_1" : 4017, "giftID_2" : 0, "giftID_3" : 0, "giftID_4" : 0}, 
"20009" : {"attID" : 20009, "icon" : 101, "attName" : 20009115, "instructions" : 20009215, "customNum" : 7, "custom_0" : 9001, "custom_1" : 9002, "custom_2" : 9003, "custom_3" : 9004, "custom_4" : 9005, "custom_5" : 9006, "custom_6" : 9007, "custom_7" : 0, "custom_8" : 0, "custom_9" : 0, "hellCustom_0" : 99001, "hellCustom_1" : 99002, "hellCustom_2" : 99003, "hellCustom_3" : 99004, "hellCustom_4" : 99005, "hellCustom_5" : 99006, "hellCustom_6" : 99007, "hellCustom_7" : 0, "hellCustom_8" : 0, "hellCustom_9" : 0, "teamCustom" : 920008, "giftNum" : 2, "giftID_0" : 4029, "giftID_1" : 4018, "giftID_2" : 0, "giftID_3" : 0, "giftID_4" : 0}
}
